instpy/__init__.py
instpy-0.0.1.dist-info/LICENSE
instpy-0.0.1.dist-info/METADATA
instpy-0.0.1.dist-info/WHEEL
instpy-0.0.1.dist-info/top_level.txt
instpy-0.0.1.dist-info/RECORD
