Metadata-Version: 2.1
Name: instpy
Version: 0.0.1
Summary: Inferencial Stadistics library
Home-page: UNKNOWN
Author: Carlos Enrique Yucra
Author-email: calollikito12000@gmail.com
License: UNKNOWN
Platform: UNKNOWN
Classifier: Intended Audience :: Education
Classifier: Programming Language :: Python :: 3
Classifier: License :: OSI Approved :: MIT License
Classifier: Operating System :: OS Independent
Requires-Python: >=3.6
License-File: LICENSE
Requires-Dist: statsmodels (>=0.12.0)
Requires-Dist: matplotlib (>=3.3.0)
Requires-Dist: numpy (>=1.19.2)
Requires-Dist: pandas (>=1.1.2)
Requires-Dist: plotly (>=4.12.0)
Requires-Dist: scipy (>=1.5.2)
